{
  "project_info": {
    "project_number": "476161322544",
    "project_id": "qriderrd",
    "storage_bucket": "qriderrd.firebasestorage.app"
  },
  "client": [
    {
      "client_info": {
        "mobilesdk_app_id": "1:476161322544:android:ae9924e7977cfaba8887f5",
        "android_client_info": {
          "package_name": "com.qriderrd"
        }
      },
      "oauth_client": [],
      "api_key": [
        {
          "current_key": "AIzaSyDNMfYPvscr_AswdYhbkMfVCtckD0uEzUA"
        }
      ],
      "services": {
        "appinvite_service": {
          "other_platform_oauth_client": []
        }
      }
    }
  ],
  "configuration_version": "1"
}
